scaleway/__init__.py
scaleway/apis/__init__.py
scaleway/apis/api_account.py
scaleway/apis/api_billing.py
scaleway/apis/api_compute.py
scaleway/apis/api_metadata.py
scaleway/tests/__init__.py
scaleway/tests/apis/__init__.py
scaleway/tests/apis/test_api.py
scaleway/tests/apis/test_api_account.py
scaleway/tests/apis/test_api_billing.py
scaleway/tests/apis/test_api_compute.py
scaleway/tests/apis/test_api_metadata.py
scaleway_sdk-1.15.0.dist-info/LICENSE
scaleway_sdk-1.15.0.dist-info/METADATA
scaleway_sdk-1.15.0.dist-info/WHEEL
scaleway_sdk-1.15.0.dist-info/top_level.txt
scaleway_sdk-1.15.0.dist-info/RECORD
